README.rst
setup.py
text2cron/__init__.py
text2cron/cronexp.py
text2cron.egg-info/PKG-INFO
text2cron.egg-info/SOURCES.txt
text2cron.egg-info/dependency_links.txt
text2cron.egg-info/requires.txt
text2cron.egg-info/top_level.txt